starstack/__init__.py
starstack/constants.py
starstack/mrcFileStack.py
starstack/particlesStar.py
starstack-0.2.14.dist-info/licenses/LICENSE
tests/__init__.py
tests/test_particlesStar.py
starstack-0.2.14.dist-info/METADATA
starstack-0.2.14.dist-info/WHEEL
starstack-0.2.14.dist-info/top_level.txt
starstack-0.2.14.dist-info/RECORD
