Metadata-Version: 2.4
Name: starstack
Version: 0.2.14
Summary: A relion star mrcs stack class
Home-page: https://github.com/rsanchezgarc/starstack
Author: Ruben Sanchez Garcia
Author-email: ruben.sanchez-garcia@stats.ox.ac.uk
Keywords: relion cryoem star stack mrcs
License-File: LICENSE
Requires-Dist: mrcfile
Requires-Dist: numpy
Requires-Dist: pandas
Requires-Dist: requests
Requires-Dist: starfile
Dynamic: author
Dynamic: author-email
Dynamic: description
Dynamic: description-content-type
Dynamic: home-page
Dynamic: keywords
Dynamic: license-file
Dynamic: requires-dist
Dynamic: summary
